.dockerignore
.travis.yml
AUTHORS
ChangeLog
Dockerfile
LICENSE
README.md
requirements.txt
setup.cfg
setup.py
test-requirements.in
test-requirements.txt
tox.ini
fake_ubersmith/__init__.py
fake_ubersmith/main.py
fake_ubersmith.egg-info/PKG-INFO
fake_ubersmith.egg-info/SOURCES.txt
fake_ubersmith.egg-info/dependency_links.txt
fake_ubersmith.egg-info/entry_points.txt
fake_ubersmith.egg-info/not-zip-safe
fake_ubersmith.egg-info/pbr.json
fake_ubersmith.egg-info/requires.txt
fake_ubersmith.egg-info/top_level.txt
fake_ubersmith/api/__init__.py
fake_ubersmith/api/administrative_local.py
fake_ubersmith/api/base.py
fake_ubersmith/api/ubersmith.py
fake_ubersmith/api/adapters/__init__.py
fake_ubersmith/api/adapters/data_store.py
fake_ubersmith/api/methods/__init__.py
fake_ubersmith/api/methods/client.py
fake_ubersmith/api/methods/order.py
fake_ubersmith/api/methods/uber.py
fake_ubersmith/api/methods/vendor_modules/__init__.py
fake_ubersmith/api/methods/vendor_modules/iweb.py
fake_ubersmith/api/utils/__init__.py
fake_ubersmith/api/utils/response.py
fake_ubersmith/api/utils/utils.py
tests/__init__.py
tests/utils.py
tests/integration/__init__.py
tests/integration/base.py
tests/integration/test_ubersmith_client.py
tests/integration/test_vendor_modules_iweb.py
tests/unit/__init__.py
tests/unit/test_main.py
tests/unit/api/__init__.py
tests/unit/api/test_administrative_local.py
tests/unit/api/test_ubersmith_base.py
tests/unit/api/methods/__init__.py
tests/unit/api/methods/test_client.py
tests/unit/api/methods/test_order.py
tests/unit/api/methods/test_uber.py
tests/unit/api/methods/vendor_modules/__init__.py
tests/unit/api/methods/vendor_modules/test_iweb.py