Metadata-Version: 1.1
Name: fake-ubersmith
Version: 0.34.0
Summary: Fake Ubersmith python web server
Home-page: https://github.com/internap/fake-ubersmith
Author: Internap Hosting
Author-email: opensource@internap.com
License: Apache Software License
Platform: UNKNOWN
Classifier: Development Status :: 5 - Production/Stable
Classifier: Intended Audience :: Developers
Classifier: Intended Audience :: Information Technology
Classifier: Intended Audience :: System Administrators
Classifier: License :: OSI Approved :: Apache Software License
Classifier: Operating System :: POSIX
Classifier: Programming Language :: Python :: 3.4
Classifier: Programming Language :: Python :: 3.5
Classifier: Topic :: Software Development :: Testing
Classifier: Topic :: System :: Emulators
